{
  "template": [
    {
      "name": "Template 1",
      "description": "This is the description of the template",
      "headerRow": 1,
      "data": [
        {
          "name": "New Country",
          "from": "input",
          "value": "C",
          "type": "string"
        },
        {
          "name": "New Product",
          "from": "input",
          "value": "D",
          "type": "string"
        },
        {
          "name": "New Date",
          "from": "input",
          "value": "M",
          "type": "date"
        },
        {
          "name": "New Price",
          "from": "input",
          "value": "F",
          "type": "number"
        },
        {
          "name": "New Test",
          "from": "input",
          "value": "AF",
          "type": "string"
        }
      ]
    }
  ]
}